sdnn/__init__.py
sdnn/__version__.py
sdnn/activation.py
sdnn/data_generator.py
sdnn/layers.py
sdnn/logger.py
sdnn/model.py
sdnn/perceptron.py
sdnn/ready.py
sdnn/schemas.py
sdnn/utils.py
sdnn-0.0.4.dist-info/LICENSE
sdnn-0.0.4.dist-info/METADATA
sdnn-0.0.4.dist-info/WHEEL
sdnn-0.0.4.dist-info/top_level.txt
sdnn-0.0.4.dist-info/RECORD
